near_lake_framework/__init__.py
near_lake_framework/near_primitives.py
near_lake_framework/py.typed
near_lake_framework/s3_fetchers.py
near_lake_framework/utils.py
near_lake_framework-0.1.3.dist-info/LICENSE-APACHE
near_lake_framework-0.1.3.dist-info/METADATA
near_lake_framework-0.1.3.dist-info/WHEEL
near_lake_framework-0.1.3.dist-info/top_level.txt
near_lake_framework-0.1.3.dist-info/RECORD
