Metadata-Version: 2.1
Name: near-lake-framework
Version: 0.1.3
Summary: Python Library to connect to the NEAR Lake S3 and stream the data
Home-page: https://github.com/frolvanya/near-lake-framework-py
Author: Ivan Frolov
Author-email: frolvanya@gmail.com
Project-URL: Bug Tracker, https://github.com/frolvanya/near-lake-framework-py/issues
Classifier: Programming Language :: Python :: 3
Classifier: License :: OSI Approved :: MIT License
Classifier: License :: OSI Approved :: Apache Software License
Classifier: Operating System :: OS Independent
Requires-Python: >=3.9
License-File: LICENSE-APACHE
Requires-Dist: asyncio>=3.4.3
Requires-Dist: dataclasses>=0.6
Requires-Dist: dataclasses-json>=0.5.7
Requires-Dist: aiobotocore>=2.3.0
Requires-Dist: requests>=2.32.2
